{
    "useConfigFiles": true,
    "plugins": {
        "@vue/cli-plugin-babel": {},
        "@vue/cli-plugin-typescript": {
            "classComponent": false,
            "useTsWithBabel": true
        },
        "@vue/cli-plugin-router": {
            "historyMode": false
        },
        "@vue/cli-plugin-vuex": {},
        "@vue/cli-plugin-eslint": {
            "config": "prettier",
            "lintOn": [
                "save"
            ]
        },
        "@vue/cli-plugin-unit-mocha": {},
        "@vue/cli-plugin-e2e-cypress": {}
    },
    "vueVersion": "3",
    "cssPreprocessor": "stylus"
}
